setup.py
bin/linguini
linguini/__init__.py
linguini/academic_layout.py
linguini/basic_layout.py
linguini/resource.py
linguini/run.py
linguini/task.py
linguini/test.py
linguini/utils.py
linguini.egg-info/PKG-INFO
linguini.egg-info/SOURCES.txt
linguini.egg-info/dependency_links.txt
linguini.egg-info/pbr.json
linguini.egg-info/top_level.txt