Metadata-Version: 1.1
Name: linguini
Version: 1.1.7
Summary: beats both spaghetti and ravioli
Home-page: UNKNOWN
Author: edward newell
Author-email: edward.newell@gmail.com
License: MIT
Keywords: pipe dream
Platform: UNKNOWN
Classifier: Development Status :: 2 - Pre-Alpha
Classifier: Intended Audience :: Science/Research
Classifier: Intended Audience :: System Administrators
Classifier: Intended Audience :: Information Technology
Classifier: Programming Language :: Python :: 2.7
Classifier: Natural Language :: English
Classifier: Topic :: Utilities
